{"bc85B79kWHExWJ4Fx+EgTA==":"rm-logo.svg","mGRkpwNF2aARBGSIZPA0LQ==":"rm-1791x1414.png","U8yIATZ11nom62g8mw2TvQ==":"echoheadon-500x442.png","8p4TLCUdcy2XxxkhMYBH5Q==":"elite-341x259.png","GKE93rmsMBJUt4oiVwuD8Q==":"full-service-restaurant.jpg","3u+Dig73ddP2mu37uQ31pw==":"club.jpg","GUrTWYiXFN5nxzlMauiJwg==":"burgerking-280x155.png","ac2i04WGb1hiCV8vgpvGHA==":"dairy-queen-logo-0280x155.png","Ak79pvBX8Nx7hAnQI0/dcg==":"peterpiperpizza280x155.png","/xJgEKFkMJUnSx1h1SUp3w==":"littlecaessars280x155.png","TzALj634OUmV+FcTPmrwHQ==":"outback-280x155.png","d2jh6gaaH6FhBGhB06WwaQ==":"101085-47874d1bfe424993bd120d6263911b6a.jpg","lMEd3Bmy1srUJFgwQ/FMWw==":"ordergirl.jpg","0lfOFGp3CaE0CU6tVuYOLA==":"fast-food-restaurant.jpg","UY5OlKrQVjTL9UpK0JbeDw==":"pizza.jpg","vNK7Jr4XP7m7rijuNKw8Uw==":"echo-swivel-right-signature.png","uh1n1/uoPnaEzLVIFXsVIg==":"echo-pos.png","bDahw9T1E1AqYVwvnhOBEQ==":"rm.svg","IhZfsPyp03rSi3KreLnaVw==":"rmlogo.svg","Uh18Hg9Rd8OsSjESiY1yaw==":"rmlogo2.svg"}